{
  "title": "春宿左省",
  "auth": "杜甫",
  "type": "五言律诗",
  "content": [
    "花隐掖垣暮",
    "啾啾栖鸟过",
    "星临万户动",
    "月傍九霄多",
    "不寝听金钥",
    "因风想玉珂",
    "明朝有封事",
    "数问夜如何？"
  ],
  "desc": "<p>        <strong>注解</strong><br>１、掖垣：因门下省、中书省地处左右两边，像人的两掖，门下省为左掖。<br>２、金钥；指开宫门的锁钥声。<br>３、珂：马铃。<br>４、封事：臣下上书奏事，防有泄漏，用黑色袋子密封，故称。      </p><p>        <strong>译文</strong><br>左偏殿矮墙遮隐花丛，日已将暮，<br>投宿的鸟儿，一群群鸣叫着飞过。<br>星临宫中，千门万户似乎在闪烁，<br>靠近天廷，所得的月光应该更多。<br>夜不敢寝，听到宫门开启的钥锁，<br>晚风飒飒，想起上朝马铃的音波。<br>明晨上朝，还有重要的大事要做，<br>心里不安，多次地探问夜漏几何？      </p><p><strong>赏析</strong><br>　 　 诗作于左拾遗任上，记叙了诚敬值宿，夜不敢寐的实况。反映了这时诗人不过是个小心谨慎的官吏罢了，字里行间也流露诗人的忠爱之情。<br>　 　        诗开头两联写景，后两联写情。自幕至夜，再自夜至晓，自晓至明，结构严谨而又灵活，叙述详明而有变化。      </p>"
}